[{"id":1,"name":"Muyao Softbrush","ttfUrl":"https://texttoimage.vector123.com/font/Muyao-Softbrush.ttf","ttfMd5":"009EA542D4B984201B30A6CF2DB555F8","ttfFileSize":4673412,"ttfSubsetUrl":"https://texttoimage.vector123.com/font-subset/Muyao-Softbrush.subset.ttf","ttfSubsetMd5":"55E37CB0CF1E68BE99E15DEB8830E40C","nameValues":{"zh-tradition":"沐瑤軟筆手寫體","zh":"沐瑶软笔手写体"}},{"id":2,"name":"Roboto Mono","ttfUrl":"https://texttoimage.vector123.com/font/RobotoMono-Bold.ttf","ttfMd5":"D6134C866FA9835BA8E9EB7F45ADF897","ttfFileSize":113628,"ttfSubsetUrl":"https://texttoimage.vector123.com/font-subset/RobotoMono-Bold.subset.ttf","ttfSubsetMd5":"EED57CC78A0ADC8B154CA7247722D774","nameValues":null},{"id":3,"name":"SetoFont","ttfUrl":"https://texttoimage.vector123.com/font/SetoFont-1.ttf","ttfMd5":"E8F777A7F9C6EA2DFC3ADD0AE9A6FB66","ttfFileSize":12473708,"ttfSubsetUrl":"https://texttoimage.vector123.com/font-subset/SetoFont-1.subset.ttf","ttfSubsetMd5":"8910F08A49E4F79111A2D57E42B35813","nameValues":{"zh-tradition":"瀨戶字體","zh":"濑户字体"}},{"id":4,"name":"Slidefu","ttfUrl":"https://texttoimage.vector123.com/font/slideyouran-Regular-1.ttf","ttfMd5":"E7748006240E0950BC4C2E9CF985E547","ttfFileSize":12640032,"ttfSubsetUrl":"https://texttoimage.vector123.com/font-subset/slideyouran-Regular-1.subset.ttf","ttfSubsetMd5":"5ACBC173B91EB674DB3F05BB2773B2C3","nameValues":{"zh-tradition":"演示悠然小楷字體","zh":"演示悠然小楷字体"}},{"id":5,"name":"Soukou Mincho","ttfUrl":"https://texttoimage.vector123.com/font/SoukouMincho-2.ttf","ttfMd5":"08C3969BB6D9631C9FBDE19742EB4C2F","ttfFileSize":9815820,"ttfSubsetUrl":"https://texttoimage.vector123.com/font-subset/SoukouMincho-2.subset.ttf","ttfSubsetMd5":"F6EF72978A1D51EDEDE0BE274233BC07","nameValues":{"zh-tradition":"裝甲明朝體","zh":"装甲明朝体"}},{"id":6,"name":"Raleway","ttfUrl":"https://texttoimage.vector123.com/font/Raleway-Regular-2.ttf","ttfMd5":"580D0778AD254335BE45BF58BB449F43","ttfFileSize":178520,"ttfSubsetUrl":"https://texttoimage.vector123.com/font-subset/Raleway-Regular-2.subset.ttf","ttfSubsetMd5":"729A805F5753F39B9F5982A416EF5778","nameValues":null},{"id":7,"name":"SpaceMono","ttfUrl":"https://texttoimage.vector123.com/font/SpaceMono-Regular.ttf","ttfMd5":"52EB73DBCE8BF4083A59ACC2E91699AD","ttfFileSize":90972,"ttfSubsetUrl":"https://texttoimage.vector123.com/font-subset/SpaceMono-Regular.subset.ttf","ttfSubsetMd5":"DEFF5F073463A9153A1B0E55A834F865","nameValues":null},{"id":8,"name":"Karla","ttfUrl":"https://texttoimage.vector123.com/font/Karla-Regular.ttf","ttfMd5":"1B55FEE684D61BFEAA762684931B1BC9","ttfFileSize":14824,"ttfSubsetUrl":"https://texttoimage.vector123.com/font-subset/Karla-Regular.subset.ttf","ttfSubsetMd5":"7674F832B2686EE1506E760820CDEEEC","nameValues":null},{"id":9,"name":"Abril Fatface","ttfUrl":"https://texttoimage.vector123.com/font/AbrilFatface-Regular.ttf","ttfMd5":"28195C14E6A271F42CA0994FAC4FB0E4","ttfFileSize":58372,"ttfSubsetUrl":"https://texttoimage.vector123.com/font-subset/AbrilFatface-Regular.subset.ttf","ttfSubsetMd5":"BBA7B3709F2DB64A6E9363E22DB2F0B3","nameValues":null},{"id":10,"name":"Archivo Black","ttfUrl":"https://texttoimage.vector123.com/font/ArchivoBlack-Regular.ttf","ttfMd5":"524A4CBDF53CDB9BB2742D2AA7A25C36","ttfFileSize":89156,"ttfSubsetUrl":"https://texttoimage.vector123.com/font-subset/ArchivoBlack-Regular.subset.ttf","ttfSubsetMd5":"D096F61D0F04251E1E2B6ECFC32C18D0","nameValues":null},{"id":11,"name":"Archivo Narrow","ttfUrl":"https://texttoimage.vector123.com/font/ArchivoNarrow-Regular.ttf","ttfMd5":"DBCD1ECF1A4B0D74289A54ED72EDC1C3","ttfFileSize":161212,"ttfSubsetUrl":"https://texttoimage.vector123.com/font-subset/ArchivoNarrow-Regular.subset.ttf","ttfSubsetMd5":"C8C6566F65C477F9D57B16B2AADEE9CF","nameValues":null},{"id":12,"name":"Arvo","ttfUrl":"https://texttoimage.vector123.com/font/Arvo-Regular.ttf","ttfMd5":"AFB50701726581F5F817FAAB8F7CF1B7","ttfFileSize":38596,"ttfSubsetUrl":"https://texttoimage.vector123.com/font-subset/Arvo-Regular.subset.ttf","ttfSubsetMd5":"48E0A51DC3C1CD5E23B68863833DB2BF","nameValues":null},{"id":13,"name":"B612","ttfUrl":"https://texttoimage.vector123.com/font/B612-Regular.ttf","ttfMd5":"E8ED14E1CDEED375C3C22BC1C4424B6F","ttfFileSize":142728,"ttfSubsetUrl":"https://texttoimage.vector123.com/font-subset/B612-Regular.subset.ttf","ttfSubsetMd5":"D6C8FC63FFE7906FC051C51C07D12080","nameValues":null},{"id":14,"name":"Bio Rhyme Expanded","ttfUrl":"https://texttoimage.vector123.com/font/BioRhymeExpanded-Regular.ttf","ttfMd5":"4423F37D8FCA1D95BE1B22FEAF6ADC41","ttfFileSize":95588,"ttfSubsetUrl":"https://texttoimage.vector123.com/font-subset/BioRhymeExpanded-Regular.subset.ttf","ttfSubsetMd5":"DB5996DA03E542BF215B1994912EAF5E","nameValues":null},{"id":15,"name":"Cairo","ttfUrl":"https://texttoimage.vector123.com/font/Cairo-Regular.ttf","ttfMd5":"E793EDB57AAF4D59AC9E943CBF091937","ttfFileSize":151580,"ttfSubsetUrl":"https://texttoimage.vector123.com/font-subset/Cairo-Regular.subset.ttf","ttfSubsetMd5":"891D8BDBB0D785FDCF2E0AA5022508F2","nameValues":null},{"id":16,"name":"Cardo","ttfUrl":"https://texttoimage.vector123.com/font/Cardo-Regular.ttf","ttfMd5":"9818302BDE1C74EAA2F0331C0B0B1189","ttfFileSize":390056,"ttfSubsetUrl":"https://texttoimage.vector123.com/font-subset/Cardo-Regular.subset.ttf","ttfSubsetMd5":"DB7B29511D85A1CEB1DFD434BF920F60","nameValues":null},{"id":17,"name":"Crimson Text","ttfUrl":"https://texttoimage.vector123.com/font/CrimsonText-Regular.ttf","ttfMd5":"62F10D46561ED0B911D42B7510D62D74","ttfFileSize":125568,"ttfSubsetUrl":"https://texttoimage.vector123.com/font-subset/CrimsonText-Regular.subset.ttf","ttfSubsetMd5":"3AE5B9ED15AADB4A794873497798464F","nameValues":null},{"id":18,"name":"Fjalla One","ttfUrl":"https://texttoimage.vector123.com/font/FjallaOne-Regular.ttf","ttfMd5":"4FA3683005FA20DD058F47B9CFD411DF","ttfFileSize":34744,"ttfSubsetUrl":"https://texttoimage.vector123.com/font-subset/FjallaOne-Regular.subset.ttf","ttfSubsetMd5":"545580AB44186EB240FEE54BBAE37AFD","nameValues":null},{"id":19,"name":"Frank Ruhl Libre","ttfUrl":"https://texttoimage.vector123.com/font/FrankRuhlLibre-Regular.ttf","ttfMd5":"8D3CC14FEC1CB9C0203F916ADAB91CEE","ttfFileSize":90780,"ttfSubsetUrl":"https://texttoimage.vector123.com/font-subset/FrankRuhlLibre-Regular.subset.ttf","ttfSubsetMd5":"9F07B74FF4914A27BF90BAC087ADCE13","nameValues":null},{"id":20,"name":"Lora","ttfUrl":"https://texttoimage.vector123.com/font/Lora-VariableFont_wght.ttf","ttfMd5":"337FA370C6BA675D1C9D3BA0D1444145","ttfFileSize":196056,"ttfSubsetUrl":"https://texttoimage.vector123.com/font-subset/Lora-VariableFont_wght.subset.ttf","ttfSubsetMd5":"D5C8C6755BDD3572A4FA839F01215DCF","nameValues":null},{"id":21,"name":"Merriweather","ttfUrl":"https://texttoimage.vector123.com/font/Merriweather-Regular.ttf","ttfMd5":"C97A9FC29652BB4AFCDAC68020E5D0F7","ttfFileSize":149092,"ttfSubsetUrl":"https://texttoimage.vector123.com/font-subset/Merriweather-Regular.subset.ttf","ttfSubsetMd5":"154E9DDA2E7CAFF98A2CE6F40914E01D","nameValues":null},{"id":22,"name":"Montserrat","ttfUrl":"https://texttoimage.vector123.com/font/Montserrat-Regular.ttf","ttfMd5":"EE6539921D713482B8CCD4D0D23961BB","ttfFileSize":245708,"ttfSubsetUrl":"https://texttoimage.vector123.com/font-subset/Montserrat-Regular.subset.ttf","ttfSubsetMd5":"7DEEE6305DE4EEA73E0026DD47EB29D2","nameValues":null},{"id":23,"name":"Muli","ttfUrl":"https://texttoimage.vector123.com/font/Muli-VariableFont_wght.ttf","ttfMd5":"E8EFEE929EB2218FDC84A27389F3968B","ttfFileSize":145808,"ttfSubsetUrl":"https://texttoimage.vector123.com/font-subset/Muli-VariableFont_wght.subset.ttf","ttfSubsetMd5":"1855DEDD964EFED175380E2334AD9BC5","nameValues":null},{"id":24,"name":"Nunito","ttfUrl":"https://texttoimage.vector123.com/font/Nunito-Regular.ttf","ttfMd5":"D2E691BC4A2B696929172CB3D22CE8BA","ttfFileSize":166700,"ttfSubsetUrl":"https://texttoimage.vector123.com/font-subset/Nunito-Regular.subset.ttf","ttfSubsetMd5":"EA59FEF1CD170C14C40343AFD3FAB121","nameValues":null},{"id":25,"name":"jf open huninn","ttfUrl":"https://texttoimage.vector123.com/font/jf-openhuninn-1.1.ttf","ttfMd5":"E9AC35C6BBBE38B480FCCE7F72D26C9D","ttfFileSize":7664060,"ttfSubsetUrl":"https://texttoimage.vector123.com/font-subset/jf-openhuninn-1.1.subset.ttf","ttfSubsetMd5":"D30D80B6F3940EEA256041C4B5C47C9C","nameValues":{"zh-tradition":"jf open 粉圓","zh":"jf open 粉圓"}},{"id":26,"name":"Oswald","ttfUrl":"https://texttoimage.vector123.com/font/Oswald-VariableFont_wght.ttf","ttfMd5":"A6E5446A7C5789AABC9B37EAAF72134D","ttfFileSize":153152,"ttfSubsetUrl":"https://texttoimage.vector123.com/font-subset/Oswald-VariableFont_wght.subset.ttf","ttfSubsetMd5":"A731395F360FC39D6D2B1A3E4AA6D306","nameValues":null},{"id":27,"name":"Permanent Marker","ttfUrl":"https://texttoimage.vector123.com/font/PermanentMarker-Regular.ttf","ttfMd5":"C863F8028C2505F92540E0BA7C379002","ttfFileSize":73620,"ttfSubsetUrl":"https://texttoimage.vector123.com/font-subset/PermanentMarker-Regular.subset.ttf","ttfSubsetMd5":"65722F8D2E46E0662CD5A9EB88F20B3E","nameValues":null},{"id":28,"name":"Playfair Display","ttfUrl":"https://texttoimage.vector123.com/font/PlayfairDisplay-VariableFont_wght.ttf","ttfMd5":"20E1565DD5C9E47BD241D99C0DD55AD1","ttfFileSize":340520,"ttfSubsetUrl":"https://texttoimage.vector123.com/font-subset/PlayfairDisplay-VariableFont_wght.subset.ttf","ttfSubsetMd5":"8265BE168C5E8D41A09006BF2907D5E1","nameValues":null},{"id":29,"name":"PT Serif","ttfUrl":"https://texttoimage.vector123.com/font/PTSerif-Regular.ttf","ttfMd5":"5F7303C0E7F09925586E218AB8FD9B19","ttfFileSize":215096,"ttfSubsetUrl":"https://texttoimage.vector123.com/font-subset/PTSerif-Regular.subset.ttf","ttfSubsetMd5":"C19E8FEAE1C6E53B7ED6E284ED8C98A4","nameValues":null},{"id":30,"name":"Rakkas","ttfUrl":"https://texttoimage.vector123.com/font/Rakkas-Regular.ttf","ttfMd5":"E3E844283693A8ADE3E5B3C39D012645","ttfFileSize":137372,"ttfSubsetUrl":"https://texttoimage.vector123.com/font-subset/Rakkas-Regular.subset.ttf","ttfSubsetMd5":"D07473D726FFA00E3E33B153C38664B0","nameValues":null},{"id":31,"name":"Rock Salt","ttfUrl":"https://texttoimage.vector123.com/font/RockSalt-Regular.ttf","ttfMd5":"1AF0B153D5633CA641BADC9E7DFE8245","ttfFileSize":119304,"ttfSubsetUrl":"https://texttoimage.vector123.com/font-subset/RockSalt-Regular.subset.ttf","ttfSubsetMd5":"92D2E8CEBC8737221C335A10E7805932","nameValues":null},{"id":32,"name":"Rubik","ttfUrl":"https://texttoimage.vector123.com/font/Rubik-Regular.ttf","ttfMd5":"B3D0902B533FF4C4F1698A2F96DDABAB","ttfFileSize":133376,"ttfSubsetUrl":"https://texttoimage.vector123.com/font-subset/Rubik-Regular.subset.ttf","ttfSubsetMd5":"2A9BD6BCA6CBB004D13A09230059CFC7","nameValues":null},{"id":33,"name":"Spectral","ttfUrl":"https://texttoimage.vector123.com/font/Spectral-Regular.ttf","ttfMd5":"7B78FF83168097BF78ED628B3ED15D9C","ttfFileSize":262596,"ttfSubsetUrl":"https://texttoimage.vector123.com/font-subset/Spectral-Regular.subset.ttf","ttfSubsetMd5":"49083DEAD83C7196BF24FCF29CBBDFB1","nameValues":null},{"id":34,"name":"Titillium Web","ttfUrl":"https://texttoimage.vector123.com/font/TitilliumWeb-Regular.ttf","ttfMd5":"ED1D014BF2B8B72F27D6AF65C69F710A","ttfFileSize":57392,"ttfSubsetUrl":"https://texttoimage.vector123.com/font-subset/TitilliumWeb-Regular.subset.ttf","ttfSubsetMd5":"A53DA253BA110168C40BFD976BAA42EE","nameValues":null},{"id":35,"name":"Varela Round","ttfUrl":"https://texttoimage.vector123.com/font/VarelaRound-Regular.ttf","ttfMd5":"159CB67FC3BC762A8C3232F0A0C6728E","ttfFileSize":125832,"ttfSubsetUrl":"https://texttoimage.vector123.com/font-subset/VarelaRound-Regular.subset.ttf","ttfSubsetMd5":"87A8DAFF161A0090B58E3A85BE2AAB91","nameValues":null},{"id":36,"name":"Vollkorn","ttfUrl":"https://texttoimage.vector123.com/font/Vollkorn-VariableFont_wght.ttf","ttfMd5":"8D634F4318355157A82864437E5E90EE","ttfFileSize":541632,"ttfSubsetUrl":"https://texttoimage.vector123.com/font-subset/Vollkorn-VariableFont_wght.subset.ttf","ttfSubsetMd5":"33C47AF61F47B65E6486B356CA718B2D","nameValues":null},{"id":37,"name":"Yanone Kaffeesatz","ttfUrl":"https://texttoimage.vector123.com/font/YanoneKaffeesatz-VariableFont_wght.ttf","ttfMd5":"D3E30C393C37D05E2A80A35B05B5A8D1","ttfFileSize":144348,"ttfSubsetUrl":"https://texttoimage.vector123.com/font-subset/YanoneKaffeesatz-VariableFont_wght.subset.ttf","ttfSubsetMd5":"B50CE6F5BD9999A7BC4A205D02C9236C","nameValues":null}]